sdm_collector/__init__.py
sdm_collector/eastron.py
sdm_collector/main.py
sdm_collector/tests.py
sdm_collector-1.0.3.data/scripts/sdm-collector
sdm_collector-1.0.3.dist-info/DESCRIPTION.rst
sdm_collector-1.0.3.dist-info/METADATA
sdm_collector-1.0.3.dist-info/RECORD
sdm_collector-1.0.3.dist-info/WHEEL
sdm_collector-1.0.3.dist-info/metadata.json
sdm_collector-1.0.3.dist-info/top_level.txt
