Metadata-Version: 2.0
Name: sdm-collector
Version: 1.0.3
Summary: Eastron SDM120 Modbus collector
Home-page: https://bitbucket.org/madron/sdm-collector
Author: Massimiliano Ravelli
Author-email: massimiliano.ravelli@gmail.com
License: MIT
Keywords: energy electricity metering
Platform: UNKNOWN
Classifier: Development Status :: 5 - Production/Stable
Classifier: Environment :: Console
Classifier: Intended Audience :: System Administrators
Classifier: Topic :: Scientific/Engineering :: Information Analysis
Classifier: License :: OSI Approved :: MIT License
Classifier: Programming Language :: Python :: 2
Classifier: Programming Language :: Python :: 2.7
Classifier: Programming Language :: Python :: 3
Classifier: Programming Language :: Python :: 3.4
Requires-Dist: pyserial (<4,>=3.0)
Requires-Dist: modbus-tk (>=0.4.3)
Requires-Dist: redis (<3,>=2.10.5)
Requires-Dist: requests (<3,>=2.9)
Requires-Dist: prometheus-client (==0.0.21)
